insightface/__init__.py
insightface/app/__init__.py
insightface/app/common.py
insightface/app/face_analysis.py
insightface/app/mask_renderer.py
insightface/commands/__init__.py
insightface/commands/insightface_cli.py
insightface/commands/model_download.py
insightface/commands/rec_add_mask_param.py
insightface/data/__init__.py
insightface/data/image.py
insightface/data/rec_builder.py
insightface/data/images/0.png
insightface/data/images/1.png
insightface/data/images/1134175.698800_32_300_152_407_-6.482666_6.482422.png
insightface/data/images/1142299.281135_31_295_166_412_-6.650146_6.649902.png
insightface/data/images/1434218.375836_62_357_136_421_-0.561279_0.561035.png
insightface/data/images/143474.752683_155_308_274_408_-6.875000_6.874756.png
insightface/data/images/145272.026683_156_220_345_380_-4.270752_4.270508.png
insightface/data/images/151636.740017_24_363_107_436_-6.742920_6.742676.png
insightface/data/images/1521367.587180_141_320_354_489_-0.953857_0.953613.png
insightface/data/images/1577606.000853_112_222_345_436_6.463623_-6.463867.png
insightface/data/images/1622113.936859_186_210_347_356_-2.834717_2.834473.png
insightface/data/images/1700255.728534_151_248_324_402_0.468262_-0.468506.png
insightface/data/images/1825562.722216_218_526_334_627_4.864746_-4.864990.png
insightface/data/images/1847592.864552_67_236_226_371_-6.669189_6.668945.png
insightface/data/images/1858190.681220_116_200_279_338_-0.144531_0.144287.png
insightface/data/images/1863285.104221_131_387_353_584_-6.777588_6.777344.png
insightface/data/images/1964086.529900_177_244_356_396_-6.499756_6.499512.png
insightface/data/images/2.png
insightface/data/images/2047153.114243_98_335_183_408_-6.531250_6.531006.png
insightface/data/images/2058163.312910_162_277_289_377_-6.697998_6.697754.png
insightface/data/images/2164081.135590_205_342_301_422_-6.707275_6.707031.png
insightface/data/images/2233529.489598_155_257_278_359_-6.075439_6.075195.png
insightface_uniubi-0.4.7.dist-info/METADATA
insightface_uniubi-0.4.7.dist-info/WHEEL
insightface_uniubi-0.4.7.dist-info/entry_points.txt
insightface_uniubi-0.4.7.dist-info/top_level.txt
insightface_uniubi-0.4.7.dist-info/zip-safe
insightface_uniubi-0.4.7.dist-info/RECORD
