Metadata-Version: 2.1
Name: insightface-uniubi
Version: 0.4.7
Summary: InsightFace Python Library
Home-page: https://github.com/deepinsight/insightface
Author: InsightFace Contributors
Author-email: contact@insightface.ai
License: MIT
Requires-Dist: numpy
Requires-Dist: onnx
Requires-Dist: tqdm
Requires-Dist: requests
Requires-Dist: matplotlib
Requires-Dist: Pillow
Requires-Dist: scipy
Requires-Dist: scikit-learn
Requires-Dist: scikit-image
Requires-Dist: easydict
Requires-Dist: cython
Requires-Dist: albumentations
Requires-Dist: prettytable
